ssci/__init__.py
ssci/abc.py
ssci/config.py
ssci/cookie.py
ssci/deployment.py
ssci/log.py
ssci/version.py
ssci/cli/__init__.py
ssci/cli/config.py
ssci/cli/dc.py
ssci/cli/git.py
ssci/cli/github.py
ssci/cli/main.py
ssci/cli/run.py
ssci/cli/utils.py
ssci/runtime/__init__.py
ssci/runtime/conf.py
ssci/runtime/main.py
ssci/runtime/utils.py
ssci/runtime/checks/__init__.py
ssci/runtime/checks/base.py
ssci/runtime/checks/gitlab_job.py
ssci/runtime/notifications/__init__.py
ssci/runtime/notifications/base.py
ssci/runtime/notifications/telegram.py
ssci/templates/__init__.py
ssci/templates/docker-compose.yml
ssci-0.2.2.dist-info/METADATA
ssci-0.2.2.dist-info/WHEEL
ssci-0.2.2.dist-info/entry_points.txt
ssci-0.2.2.dist-info/top_level.txt
ssci-0.2.2.dist-info/RECORD
